aiounittest/__init__.py
aiounittest/case.py
aiounittest/helpers.py
aiounittest/mock.py
aiounittest/py.typed
aiounittest-1.4.2.dist-info/LICENSE
aiounittest-1.4.2.dist-info/METADATA
aiounittest-1.4.2.dist-info/WHEEL
aiounittest-1.4.2.dist-info/top_level.txt
aiounittest-1.4.2.dist-info/RECORD
