Metadata-Version: 2.1
Name: aiounittest
Version: 1.4.2
Summary: Test asyncio code more easily.
Home-page: https://github.com/kwarunek/aiounittest
Author: Krzysztof Warunek
Author-email: krzysztof@warunek.net
License: MIT
Keywords: asyncio,async,unittest,coroutine
Platform: UNKNOWN
Classifier: License :: OSI Approved :: MIT License
Classifier: Programming Language :: Python :: 3.4
Classifier: Programming Language :: Python :: 3.5
Classifier: Programming Language :: Python :: 3.6
Classifier: Programming Language :: Python :: 3.7
Classifier: Programming Language :: Python :: 3.8
Classifier: Programming Language :: Python :: 3.9
Classifier: Programming Language :: Python :: 3.10
License-File: LICENSE
